{
  "/blog-c46": {
    "__comp": "a6aa9e1f",
    "__context": {
      "plugin": "36994c47"
    },
    "sidebar": "814f3328",
    "items": [
      {
        "content": "191048f1"
      },
      {
        "content": "7661071f"
      },
      {
        "content": "f4f34a3a"
      }
    ],
    "__props": "c15d9823"
  },
  "/blog/archive-182": {
    "__comp": "9e4087bc",
    "__context": {
      "plugin": "36994c47"
    },
    "__props": "f81c1134"
  },
  "/blog/authors-0b7": {
    "__comp": "621db11d",
    "__context": {
      "data": {
        "blogMetadata": "acecf23e"
      },
      "plugin": "36994c47"
    },
    "sidebar": "814f3328",
    "__props": "ef8b811a"
  },
  "/blog/authors/yijiong-a80": {
    "__comp": "33fc5bb8",
    "__context": {
      "data": {
        "blogMetadata": "acecf23e"
      },
      "plugin": "36994c47"
    },
    "items": [
      {
        "content": "191048f1"
      },
      {
        "content": "7661071f"
      },
      {
        "content": "f4f34a3a"
      }
    ],
    "sidebar": "814f3328",
    "__props": "207a28ce"
  },
  "/blog/mdx-blog-post-e9f": {
    "__comp": "ccc49370",
    "__context": {
      "data": {
        "blogMetadata": "acecf23e"
      },
      "plugin": "36994c47"
    },
    "sidebar": "814f3328",
    "content": "59362658"
  },
  "/blog/tags-287": {
    "__comp": "01a85c17",
    "__context": {
      "plugin": "36994c47"
    },
    "sidebar": "814f3328",
    "__props": "3a2db09e"
  },
  "/blog/tags/docusaurus-bec": {
    "__comp": "6875c492",
    "__context": {
      "plugin": "36994c47"
    },
    "sidebar": "814f3328",
    "items": [
      {
        "content": "7661071f"
      },
      {
        "content": "f4f34a3a"
      }
    ],
    "__props": "3217192f"
  },
  "/blog/tags/facebook-858": {
    "__comp": "6875c492",
    "__context": {
      "plugin": "36994c47"
    },
    "sidebar": "814f3328",
    "items": [
      {
        "content": "7661071f"
      }
    ],
    "__props": "e5aefb32"
  },
  "/blog/tags/hello-4ad": {
    "__comp": "6875c492",
    "__context": {
      "plugin": "36994c47"
    },
    "sidebar": "814f3328",
    "items": [
      {
        "content": "7661071f"
      }
    ],
    "__props": "f82cd581"
  },
  "/blog/tags/travelling-b99": {
    "__comp": "6875c492",
    "__context": {
      "plugin": "36994c47"
    },
    "sidebar": "814f3328",
    "items": [
      {
        "content": "191048f1"
      }
    ],
    "__props": "e46475b5"
  },
  "/blog/trip to Beijing InnerMongolia-8b1": {
    "__comp": "ccc49370",
    "__context": {
      "data": {
        "blogMetadata": "acecf23e"
      },
      "plugin": "36994c47"
    },
    "sidebar": "814f3328",
    "content": "3c5d0b21"
  },
  "/blog/welcome-d2b": {
    "__comp": "ccc49370",
    "__context": {
      "data": {
        "blogMetadata": "acecf23e"
      },
      "plugin": "36994c47"
    },
    "sidebar": "814f3328",
    "content": "d9f32620"
  },
  "/markdown-page-3d7": {
    "__comp": "1f391b9e",
    "__context": {
      "plugin": "a7456010"
    },
    "content": "393be207"
  },
  "/docs-1ca": {
    "__comp": "5e95c892",
    "__context": {
      "plugin": "aba21aa0"
    }
  },
  "/docs-e92": {
    "__comp": "a7bd4aaa",
    "__props": "0058b4c6"
  },
  "/docs-0f7": {
    "__comp": "a94703ab"
  },
  "/docs/category/investment-2bd": {
    "__comp": "14eb3368",
    "__props": "9e5129d5"
  },
  "/docs/category/技術-b84": {
    "__comp": "14eb3368",
    "__props": "9e52c7eb"
  },
  "/docs/category/自媒體兒-728": {
    "__comp": "14eb3368",
    "__props": "c8ae67e5"
  },
  "/docs/investment/indexinvestmnet-131": {
    "__comp": "17896441",
    "content": "17999d79"
  },
  "/docs/self-media/indexinvestmnet-903": {
    "__comp": "17896441",
    "content": "3c40839c"
  },
  "/docs/self-media/tiktok-c19": {
    "__comp": "17896441",
    "content": "415263fa"
  },
  "/docs/tech/dyin-ab5": {
    "__comp": "17896441",
    "content": "fb1f6cfc"
  },
  "/docs/tech/Service-ExecStart-Path-Aliyun-3cf": {
    "__comp": "17896441",
    "content": "c39cfa42"
  },
  "/-e5f": {
    "__comp": "1df93b7f",
    "__context": {
      "plugin": "a7456010"
    },
    "config": "5e9f5e1a"
  }
}